http_okapi/__init__.py
http_okapi/cherrypy.py
http_okapi/okapi.html
http_okapi/okapibg.png
http_okapi-1.0.0.dist-info/LICENSE.txt
http_okapi-1.0.0.dist-info/METADATA
http_okapi-1.0.0.dist-info/RECORD
http_okapi-1.0.0.dist-info/WHEEL
http_okapi-1.0.0.dist-info/namespace_packages.txt
http_okapi-1.0.0.dist-info/top_level.txt
