Metadata-Version: 2.1
Name: http-okapi
Version: 1.0.0
Summary: A tool for working with HTTP APIs
Home-page: https://github.com/jaraco/http-okapi
Author: Jason R. Coombs
Author-email: jaraco@jaraco.com
License: UNKNOWN
Platform: UNKNOWN
Classifier: Development Status :: 5 - Production/Stable
Classifier: Intended Audience :: Developers
Classifier: License :: OSI Approved :: MIT License
Classifier: Programming Language :: Python :: 2.7
Classifier: Programming Language :: Python :: 3
Requires-Python: >=2.7
Provides-Extra: docs
Provides-Extra: testing
